pslines/__init__.py
pslines/pslines.py
pslines-0.1.4.dist-info/METADATA
pslines-0.1.4.dist-info/WHEEL
pslines-0.1.4.dist-info/RECORD
